MANIFEST.in
RELEASE-VERSION
get_git_version.py
setup.py
py_tkb.egg-info/PKG-INFO
py_tkb.egg-info/SOURCES.txt
py_tkb.egg-info/dependency_links.txt
py_tkb.egg-info/entry_points.txt
py_tkb.egg-info/requires.txt
py_tkb.egg-info/top_level.txt
src/__init__.py
src/client.py
src/main.py