Metadata-Version: 1.0
Name: py-tkb
Version: 0.1.0
Summary: Client for tkbd daemon
Home-page: http://github.com/bwesterb/py-tkb/
Author: Bas Westerbaan
Author-email: bas@westerbaan.name
License: UNKNOWN
Platform: UNKNOWN
